pafit/CHANGELOG.rst
pafit/LICENSE.txt
pafit/README.rst
pafit/__init__.py
pafit/fit_kinematic_pa.py
pafit-2.0.8.dist-info/METADATA
pafit-2.0.8.dist-info/WHEEL
pafit-2.0.8.dist-info/top_level.txt
pafit-2.0.8.dist-info/zip-safe
pafit-2.0.8.dist-info/RECORD
