Metadata-Version: 2.1
Name: pafit
Version: 2.0.8
Summary: PaFit: Galaxies Kinematic Position Angle Fitting
Home-page: https://purl.org/cappellari/software
Author: Michele Cappellari
Author-email: michele.cappellari@physics.ox.ac.uk
License: Other/Proprietary License
Classifier: Development Status :: 5 - Production/Stable
Classifier: Intended Audience :: Developers
Classifier: Intended Audience :: Science/Research
Classifier: Operating System :: OS Independent
Classifier: Programming Language :: Python :: 3
Requires-Dist: numpy
Requires-Dist: matplotlib
Requires-Dist: plotbin
